net163
