Metadata-Version: 1.1
Name: net163
Version: 1.1.2
Summary: html text parser,get the content form html page
Home-page: https://pypi.python.org/pypi
Author: liu
Author-email: langdao5@aol.com
License: MIT
Platform: UNKNOWN
Classifier: Environment :: Web Environment
Classifier: Intended Audience :: Developers
Classifier: Operating System :: OS Independent
Classifier: Topic :: Text Processing :: Indexing
Classifier: Topic :: Utilities
Classifier: Topic :: Internet
Classifier: Topic :: Software Development :: Libraries :: Python Modules
Classifier: Programming Language :: Python
Classifier: Programming Language :: Python :: 3
Classifier: Programming Language :: Python :: 3.4
Classifier: Programming Language :: Python :: 3.5
Classifier: Programming Language :: Python :: 3.6
